banking_shared_utils/__init__.py
banking_shared_utils/constants.py
banking_shared_utils/exception_structures.py
banking_shared_utils/logging.py
banking_shared_utils/utils.py
banking_shared_utils/back/__init__.py
banking_shared_utils/back/exception_codes.py
banking_shared_utils/back/state_codes.py
banking_shared_utils/dealers/__init__.py
banking_shared_utils/dealers/exception_codes.py
banking_shared_utils/dealers/state_codes.py
banking_shared_utils-0.1.3.dist-info/METADATA
banking_shared_utils-0.1.3.dist-info/WHEEL
banking_shared_utils-0.1.3.dist-info/top_level.txt
banking_shared_utils-0.1.3.dist-info/RECORD
