Metadata-Version: 2.1
Name: banking-shared-utils
Version: 0.1.3
Summary: Shared extensions for MoneyPortal infrastructure
Home-page: https://pypi.org/project/banking_shared_utils/
Download-URL: https://pypi.org/project/banking_shared_utils/
Maintainer: Edward Azizov
Maintainer-email: edazizovv@gmail.com
License: Proprietary
Requires-Python: >=3.10
